<?xml version="1.0" encoding="utf-8" ?>
<!-- SQL XML created by WWW SQL Designer, https://github.com/ondras/wwwsqldesigner/ -->
<!-- Active URL: http://ondras.zarovi.cz/sql/demo/?keyword=dd_tyhou -->
<sql>
<datatypes db="mysql">
      <group label="Numeric" color="rgb(238,238,170)">
        <type label="Integer" length="0" sql="INTEGER" quote=""/>
        <type label="TINYINT" length="0" sql="TINYINT" quote=""/>
        <type label="SMALLINT" length="0" sql="SMALLINT" quote=""/>
        <type label="MEDIUMINT" length="0" sql="MEDIUMINT" quote=""/>
        <type label="INT" length="0" sql="INT" quote=""/>
        <type label="BIGINT" length="0" sql="BIGINT" quote=""/>
        <type label="Decimal" length="1" sql="DECIMAL" re="DEC" quote=""/>
        <type label="Single precision" length="0" sql="FLOAT" quote=""/>
        <type label="Double precision" length="0" sql="DOUBLE" re="DOUBLE" quote=""/>
      </group>
      <group label="Character" color="rgb(255,200,200)">
        <type label="Char" length="1" sql="CHAR" quote="'"/>
        <type label="Varchar" length="1" sql="VARCHAR" quote="'"/>
        <type label="Text" length="0" sql="MEDIUMTEXT" re="TEXT" quote="'"/>
        <type label="Binary" length="1" sql="BINARY" quote="'"/>
        <type label="Varbinary" length="1" sql="VARBINARY" quote="'"/>
        <type label="BLOB" length="0" sql="BLOB" re="BLOB" quote="'"/>
      </group>
      <group label="Date &amp; Time" color="rgb(200,255,200)">
        <type label="Date" length="0" sql="DATE" quote="'"/>
        <type label="Time" length="0" sql="TIME" quote="'"/>
        <type label="Datetime" length="0" sql="DATETIME" quote="'"/>
        <type label="Year" length="0" sql="YEAR" quote=""/>
        <type label="Timestamp" length="0" sql="TIMESTAMP" quote="'"/>
      </group>
      <group label="Miscellaneous" color="rgb(200,200,255)">
        <type label="ENUM" length="1" sql="ENUM" quote=""/>
        <type label="SET" length="1" sql="SET" quote=""/>
        <type label="Bit" length="0" sql="bit" quote=""/>
      </group>
    </datatypes><table x="246" y="370" name="poll">
<row name="id" null="1" autoincrement="1">
<datatype>INTEGER</datatype>
<default>NULL</default></row>
<row name="poll_type_id" null="1" autoincrement="0">
<datatype>INTEGER</datatype>
<default>NULL</default><relation table="poll_type" row="id" />
</row>
<row name="poll_sum_type_id" null="1" autoincrement="0">
<datatype>INTEGER</datatype>
<default>NULL</default><relation table="poll_sum_type" row="id" />
</row>
<row name="discussion_id" null="1" autoincrement="0">
<datatype>INTEGER</datatype>
<default>NULL</default><relation table="discussion" row="id" />
</row>
<row name="user_id" null="1" autoincrement="0">
<datatype>INTEGER</datatype>
<default>NULL</default><relation table="user" row="id" />
</row>
<row name="private_password" null="1" autoincrement="0">
<datatype>VARCHAR(140)</datatype>
<default>NULL</default></row>
<row name="created" null="0" autoincrement="0">
<datatype>TIMESTAMP</datatype>
<default>CURRENT_TIMESTAMP</default></row>
<row name="modified" null="0" autoincrement="0">
<datatype>TIMESTAMP</datatype>
</row>
<key type="PRIMARY" name="">
<part>id</part>
</key>
<key type="UNIQUE" name="">
<part>discussion_id</part>
</key>
</table>
<table x="465" y="412" name="candidate">
<row name="id" null="1" autoincrement="1">
<datatype>INTEGER</datatype>
<default>NULL</default></row>
<row name="poll_id" null="1" autoincrement="0">
<datatype>INTEGER</datatype>
<default>NULL</default><relation table="poll" row="id" />
</row>
<row name="discussion_id" null="1" autoincrement="0">
<datatype>INTEGER</datatype>
<default>NULL</default><relation table="discussion" row="id" />
</row>
<row name="user_id" null="1" autoincrement="0">
<datatype>INTEGER</datatype>
<default>NULL</default><relation table="user" row="id" />
</row>
<row name="created" null="0" autoincrement="0">
<datatype>TIMESTAMP</datatype>
<default>CURRENT_TIMESTAMP</default></row>
<row name="modified" null="0" autoincrement="0">
<datatype>TIMESTAMP</datatype>
</row>
<key type="PRIMARY" name="">
<part>id</part>
</key>
<key type="UNIQUE" name="">
<part>discussion_id</part>
</key>
</table>
<table x="243" y="640" name="discussion">
<row name="id" null="1" autoincrement="1">
<datatype>INTEGER</datatype>
<default>NULL</default></row>
<row name="subject" null="1" autoincrement="0">
<datatype>VARCHAR(140)</datatype>
<default>NULL</default></row>
<row name="text" null="1" autoincrement="0">
<datatype>MEDIUMTEXT</datatype>
<default>NULL</default></row>
<row name="created" null="0" autoincrement="0">
<datatype>TIMESTAMP</datatype>
<default>CURRENT_TIMESTAMP</default></row>
<row name="modified" null="0" autoincrement="0">
<datatype>TIMESTAMP</datatype>
</row>
<key type="PRIMARY" name="">
<part>id</part>
</key>
</table>
<table x="455" y="609" name="comment">
<row name="id" null="1" autoincrement="1">
<datatype>INTEGER</datatype>
<default>NULL</default></row>
<row name="discussion_id" null="1" autoincrement="0">
<datatype>INTEGER</datatype>
<default>NULL</default><relation table="discussion" row="id" />
</row>
<row name="text" null="1" autoincrement="0">
<datatype>MEDIUMTEXT</datatype>
<default>NULL</default></row>
<row name="user_id" null="1" autoincrement="0">
<datatype>INTEGER</datatype>
<default>NULL</default><relation table="user" row="id" />
</row>
<row name="created" null="0" autoincrement="0">
<datatype>TIMESTAMP</datatype>
<default>CURRENT_TIMESTAMP</default></row>
<row name="modified" null="0" autoincrement="0">
<datatype>TIMESTAMP</datatype>
</row>
<key type="PRIMARY" name="">
<part>id</part>
</key>
</table>
<table x="660" y="608" name="comment_tree">
<row name="id" null="1" autoincrement="1">
<datatype>INTEGER</datatype>
<default>NULL</default></row>
<row name="parent_id" null="1" autoincrement="0">
<datatype>INTEGER</datatype>
<default>NULL</default><relation table="comment" row="id" />
</row>
<row name="child_id" null="1" autoincrement="0">
<datatype>INTEGER</datatype>
<default>NULL</default><relation table="comment" row="id" />
</row>
<row name="path_length" null="1" autoincrement="0">
<datatype>INTEGER</datatype>
<default>NULL</default></row>
<row name="created" null="0" autoincrement="0">
<datatype>TIMESTAMP</datatype>
<default>CURRENT_TIMESTAMP</default></row>
<row name="modified" null="0" autoincrement="0">
<datatype>TIMESTAMP</datatype>
</row>
<key type="PRIMARY" name="">
<part>id</part>
</key>
</table>
<table x="52" y="415" name="poll_type">
<row name="id" null="1" autoincrement="1">
<datatype>INTEGER</datatype>
<default>NULL</default></row>
<row name="name" null="0" autoincrement="0">
<datatype>VARCHAR(255)</datatype>
<default>'NULL'</default></row>
<row name="created" null="0" autoincrement="0">
<datatype>TIMESTAMP</datatype>
<default>CURRENT_TIMESTAMP</default></row>
<row name="modified" null="0" autoincrement="0">
<datatype>TIMESTAMP</datatype>
</row>
<key type="PRIMARY" name="">
<part>id</part>
</key>
<key type="UNIQUE" name="">
<part>name</part>
</key>
</table>
<table x="58" y="216" name="tag">
<row name="id" null="1" autoincrement="1">
<datatype>INTEGER</datatype>
<default>NULL</default></row>
<row name="name" null="1" autoincrement="0">
<datatype>VARCHAR(50)</datatype>
<default>NULL</default></row>
<row name="created" null="0" autoincrement="0">
<datatype>TIMESTAMP</datatype>
<default>CURRENT_TIMESTAMP</default></row>
<row name="modified" null="0" autoincrement="0">
<datatype>TIMESTAMP</datatype>
</row>
<key type="PRIMARY" name="">
<part>id</part>
</key>
<key type="UNIQUE" name="">
<part>name</part>
</key>
</table>
<table x="250" y="206" name="poll_tag">
<row name="id" null="1" autoincrement="1">
<datatype>INTEGER</datatype>
<default>NULL</default></row>
<row name="poll_id" null="1" autoincrement="0">
<datatype>INTEGER</datatype>
<default>NULL</default><relation table="poll" row="id" />
</row>
<row name="tag_id" null="1" autoincrement="0">
<datatype>INTEGER</datatype>
<default>NULL</default><relation table="tag" row="id" />
</row>
<row name="created" null="0" autoincrement="0">
<datatype>TIMESTAMP</datatype>
<default>CURRENT_TIMESTAMP</default></row>
<row name="modified" null="0" autoincrement="0">
<datatype>TIMESTAMP</datatype>
</row>
<key type="PRIMARY" name="">
<part>id</part>
</key>
<key type="UNIQUE" name="">
<part>poll_id</part>
<part>tag_id</part>
</key>
</table>
<table x="471" y="204" name="ballot">
<row name="id" null="1" autoincrement="1">
<datatype>INTEGER</datatype>
<default>NULL</default></row>
<row name="poll_id" null="1" autoincrement="0">
<datatype>INTEGER</datatype>
<default>NULL</default><relation table="poll" row="id" />
</row>
<row name="user_id" null="1" autoincrement="0">
<datatype>INTEGER</datatype>
<default>NULL</default><relation table="user" row="id" />
</row>
<row name="candidate_id" null="1" autoincrement="0">
<datatype>INTEGER</datatype>
<default>NULL</default><relation table="candidate" row="id" />
</row>
<row name="rank" null="1" autoincrement="0">
<datatype>INTEGER</datatype>
<default>NULL</default></row>
<row name="created" null="0" autoincrement="0">
<datatype>TIMESTAMP</datatype>
<default>CURRENT_TIMESTAMP</default></row>
<row name="modified" null="0" autoincrement="0">
<datatype>TIMESTAMP</datatype>
</row>
<key type="PRIMARY" name="">
<part>id</part>
</key>
<key type="UNIQUE" name="">
<part>poll_id</part>
<part>user_id</part>
<part>candidate_id</part>
</key>
</table>
<table x="177" y="30" name="user">
<row name="id" null="1" autoincrement="1">
<datatype>INTEGER</datatype>
<default>NULL</default></row>
<row name="ip_address" null="1" autoincrement="0">
<datatype>VARCHAR(255)</datatype>
<default>NULL</default></row>
<row name="created" null="0" autoincrement="0">
<datatype>TIMESTAMP</datatype>
<default>CURRENT_TIMESTAMP</default></row>
<row name="modified" null="0" autoincrement="0">
<datatype>TIMESTAMP</datatype>
</row>
<key type="PRIMARY" name="">
<part>id</part>
</key>
</table>
<table x="368" y="27" name="full_user">
<row name="id" null="1" autoincrement="1">
<datatype>INTEGER</datatype>
<default>NULL</default></row>
<row name="user_id" null="1" autoincrement="0">
<datatype>INTEGER</datatype>
<default>NULL</default><relation table="user" row="id" />
</row>
<row name="name" null="1" autoincrement="0">
<datatype>VARCHAR(255)</datatype>
<default>NULL</default></row>
<row name="password_encrypted" null="1" autoincrement="0">
<datatype>VARCHAR(512)</datatype>
<default>NULL</default></row>
<row name="created" null="0" autoincrement="0">
<datatype>DATETIME</datatype>
<default>CURRENT_TIMESTAMP</default></row>
<row name="modified" null="0" autoincrement="0">
<datatype>TIMESTAMP</datatype>
</row>
<key type="PRIMARY" name="">
<part>id</part>
</key>
</table>
<table x="35" y="632" name="poll_sum_type">
<row name="id" null="1" autoincrement="1">
<datatype>INTEGER</datatype>
<default>NULL</default></row>
<row name="name" null="0" autoincrement="0">
<datatype>VARCHAR(255)</datatype>
<default>'NULL'</default></row>
<row name="created" null="0" autoincrement="0">
<datatype>TIMESTAMP</datatype>
<default>CURRENT_TIMESTAMP</default></row>
<row name="modified" null="0" autoincrement="0">
<datatype>TIMESTAMP</datatype>
</row>
<key type="PRIMARY" name="">
<part>id</part>
</key>
<key type="UNIQUE" name="">
<part>name</part>
</key>
</table>
<table x="457" y="813" name="comment_rank">
<row name="id" null="1" autoincrement="1">
<datatype>INTEGER</datatype>
<default>NULL</default></row>
<row name="comment_id" null="1" autoincrement="0">
<datatype>INTEGER</datatype>
<default>NULL</default><relation table="comment" row="id" />
</row>
<row name="user_id" null="1" autoincrement="0">
<datatype>INTEGER</datatype>
<default>NULL</default><relation table="user" row="id" />
</row>
<row name="rank" null="1" autoincrement="0">
<datatype>INTEGER</datatype>
<default>NULL</default></row>
<row name="created" null="0" autoincrement="0">
<datatype>TIMESTAMP</datatype>
<default>CURRENT_TIMESTAMP</default></row>
<row name="modified" null="0" autoincrement="0">
<datatype>TIMESTAMP</datatype>
<default>'NULL'</default></row>
<key type="PRIMARY" name="">
<part>id</part>
</key>
<key type="UNIQUE" name="">
<part>comment_id</part>
<part>user_id</part>
</key>
</table>
</sql>
